mlregistry/__init__.py
mlregistry/accessors.py
mlregistry/core.py
mlregistry/registry.py
mlregistry-1.2.3.dist-info/LICENSE
mlregistry-1.2.3.dist-info/METADATA
mlregistry-1.2.3.dist-info/WHEEL
mlregistry-1.2.3.dist-info/RECORD
