Metadata-Version: 2.3
Name: mlregistry
Version: 1.2.3
Summary: A simple package to track python objects.
License: MIT
Author: mr-mapache
Author-email: eric.m.cardozo@mi.unc.edu.ar
Requires-Python: >=3.12,<4.0
Classifier: License :: OSI Approved :: MIT License
Classifier: Programming Language :: Python :: 3
Classifier: Programming Language :: Python :: 3.12
Classifier: Programming Language :: Python :: 3.13
Project-URL: Repository, https://github.com/mr-mapache/ml-registry
